json_environ/__init__.py
json_environ/json_environ.py
json_environ-0.1.1.dist-info/DESCRIPTION.rst
json_environ-0.1.1.dist-info/METADATA
json_environ-0.1.1.dist-info/RECORD
json_environ-0.1.1.dist-info/WHEEL
json_environ-0.1.1.dist-info/metadata.json
json_environ-0.1.1.dist-info/top_level.txt
