Metadata-Version: 2.0
Name: json-environ
Version: 0.1.1
Summary: Utilize environment variables from JSON file to configure your Python application.
Home-page: https://github.com/yusufkaracin/json_environ
Author: Yusuf Karaçin
Author-email: ysfbkrcn@gmail.com
License: MIT license
Keywords: json environment variables configuration
Platform: UNKNOWN
Classifier: Development Status :: 2 - Pre-Alpha
Classifier: Intended Audience :: Developers
Classifier: License :: OSI Approved :: MIT License
Classifier: Natural Language :: English
Classifier: Programming Language :: Python :: 3
Classifier: Programming Language :: Python :: 3.3
Classifier: Programming Language :: Python :: 3.4
Classifier: Programming Language :: Python :: 3.5
